openapi_client_gen/__init__.py
openapi_client_gen/cli.py
openapi_client_gen/models.py
openapi_client_gen/openapi.json
openapi_client_gen/parser.py
openapi_client_gen/py.typed
openapi_client_gen/utils.py
openapi_client_gen/generators/__init__.py
openapi_client_gen/generators/schemas.py
openapi_client_gen/generators/service.py
openapi_client_gen/templates/service.py.jinja2
openapi_client_gen-0.3.0.dist-info/METADATA
openapi_client_gen-0.3.0.dist-info/WHEEL
openapi_client_gen-0.3.0.dist-info/entry_points.txt
openapi_client_gen-0.3.0.dist-info/RECORD
