Metadata-Version: 2.4
Name: openapi-client-gen
Version: 0.3.0
Summary: Generate Python async clients from OpenAPI specs with ExternalService pattern
Requires-Python: >=3.10
Requires-Dist: external-service
Requires-Dist: jinja2>=3.0
Requires-Dist: pydantic>=2.0
Provides-Extra: dev
Requires-Dist: pytest-cov>=4.0; extra == 'dev'
Requires-Dist: pytest>=7.0; extra == 'dev'
Requires-Dist: ruff>=0.1; extra == 'dev'
Provides-Extra: schemas
Requires-Dist: datamodel-code-generator>=0.25; extra == 'schemas'
